cmfd_handler/__init__.py
cmfd_handler/io.py
cmfd_handler/pet.py
cmfd_handler/prec.py
cmfd_handler/units.py
config/vars.yaml
cmfd_handler-0.1.2.dist-info/METADATA
cmfd_handler-0.1.2.dist-info/WHEEL
cmfd_handler-0.1.2.dist-info/RECORD
