Metadata-Version: 2.1
Name: cmfd-handler
Version: 0.1.2
Summary: 
License: CC-BY-4.0
Author: SongshGeo
Author-email: songshgeo@gmail.com
Requires-Python: >=3.8.1,<4.0
Classifier: License :: Other/Proprietary License
Classifier: Programming Language :: Python :: 3
Classifier: Programming Language :: Python :: 3.9
Classifier: Programming Language :: Python :: 3.10
Classifier: Programming Language :: Python :: 3.11
Requires-Dist: cf-xarray (>=0.8.0)
Requires-Dist: geopandas (>=0,<1)
Requires-Dist: hydra-core (==1.3.*)
Requires-Dist: loguru (>=0.7.2)
Requires-Dist: metpy (>=1.4.0)
Requires-Dist: netcdf4 (>=1.6.5)
Requires-Dist: pandas (>=1.5)
Requires-Dist: pint-xarray (>=0.3)
Requires-Dist: pyet (>=1.2.2)
Requires-Dist: rioxarray (>=0.13.4)
Requires-Dist: seaborn (>=0.12.2)
Requires-Dist: tqdm (>=4.66.4)
Requires-Dist: typing-extensions (>=4.11.0)
